redkyn/__init__.py
redkyn/exceptions.py
redkyn/canvas/__init__.py
redkyn/canvas/exceptions.py
redkyn/tests/__init__.py
redkyn/tests/canvas_tests.py
redkyn/tests/utils.py
redkyn_common-1.0.1.dist-info/LICENSE
redkyn_common-1.0.1.dist-info/METADATA
redkyn_common-1.0.1.dist-info/WHEEL
redkyn_common-1.0.1.dist-info/top_level.txt
redkyn_common-1.0.1.dist-info/RECORD
