Metadata-Version: 2.1
Name: redkyn-common
Version: 1.0.1
Summary: Common libraries for Redkyn projects
Home-page: https://github.com/redkyn/redkyn-common
Author: Natasha Jarus and Islam Elnabarawi
Author-email: jarus@mst.edu
License: UNKNOWN
Platform: UNKNOWN
Classifier: Development Status :: 4 - Beta
Classifier: Intended Audience :: Education
Classifier: Topic :: Education
Classifier: License :: OSI Approved :: MIT License
Classifier: Programming Language :: Python :: 3
Classifier: Programming Language :: Python :: 3 :: Only
Classifier: Programming Language :: Python :: 3.4
Classifier: Programming Language :: Python :: 3.5
Classifier: Programming Language :: Python :: 3.6
Classifier: Programming Language :: Python :: 3.7
Requires-Python: >=3.4
Requires-Dist: requests (>=2.20.0)
Requires-Dist: typing (>=3.5) ; python_version < "3.5"
